<?xml version="1.0"?>
<opencv_storage>
<stage7>
  <maxWeakCount>18</maxWeakCount>
  <stageThreshold>-1.5857295989990234e+00</stageThreshold>
  <weakClassifiers>
    <_>
      <internalNodes>
        0 -1 22665 3.0123019218444824e-01</internalNodes>
      <leafValues>
        -7.8704929351806641e-01 -3.4496434032917023e-02</leafValues></_>
    <_>
      <internalNodes>
        0 -1 52520 4.9355230294167995e-03</internalNodes>
      <leafValues>
        -3.6246863007545471e-01 2.5012990832328796e-01</leafValues></_>
    <_>
      <internalNodes>
        0 -1 35430 -1.1179423332214355e-01</internalNodes>
      <leafValues>
        7.0661646127700806e-01 -1.4701774716377258e-01</leafValues></_>
    <_>
      <internalNodes>
        0 -1 65961 -5.4183460772037506e-02</internalNodes>
      <leafValues>
        2.0290207862854004e-01 -4.2862570285797119e-01</leafValues></_>
    <_>
      <internalNodes>
        0 -1 54483 -1.3987327925860882e-02</internalNodes>
      <leafValues>
        4.0430754423141479e-01 -1.5272922813892365e-01</leafValues></_>
    <_>
      <internalNodes>
        0 -1 49371 -8.4776990115642548e-04</internalNodes>
      <leafValues>
        4.3319886922836304e-01 -1.6765499114990234e-01</leafValues></_>
    <_>
      <internalNodes>
        0 -1 7329 4.4841365888714790e-04</internalNodes>
      <leafValues>
        1.5141253173351288e-01 -4.3631941080093384e-01</leafValues></_>
    <_>
      <internalNodes>
        0 -1 74758 -6.4106419449672103e-04</internalNodes>
      <leafValues>
        -6.8645399808883667e-01 1.2872013449668884e-01</leafValues></_>
    <_>
      <internalNodes>
        0 -1 43542 -2.1177758462727070e-03</internalNodes>
      <leafValues>
        5.4199928045272827e-01 -1.4315392076969147e-01</leafValues></_>
    <_>
      <internalNodes>
        0 -1 42908 9.8821120336651802e-03</internalNodes>
      <leafValues>
        -1.1544333398342133e-01 6.9194561243057251e-01</leafValues></_>
    <_>
      <internalNodes>
        0 -1 10184 7.1018177550286055e-04</internalNodes>
      <leafValues>
        1.4672261476516724e-01 -5.1554733514785767e-01</leafValues></_>
    <_>
      <internalNodes>
        0 -1 37801 -9.5174816669896245e-04</internalNodes>
      <leafValues>
        4.1420143842697144e-01 -1.5617641806602478e-01</leafValues></_>
    <_>
      <internalNodes>
        0 -1 3373 -4.0626310510560870e-04</internalNodes>
      <leafValues>
        -4.6581429243087769e-01 1.6413912177085876e-01</leafValues></_>
    <_>
      <internalNodes>
        0 -1 65455 5.1497821696102619e-03</internalNodes>
      <leafValues>
        7.3668256402015686e-02 -1.1297726631164551e+00</leafValues></_>
    <_>
      <internalNodes>
        0 -1 60535 8.0930301919579506e-04</internalNodes>
      <leafValues>
        -2.3590403795242310e-01 3.1016403436660767e-01</leafValues></_>
    <_>
      <internalNodes>
        0 -1 43345 1.3363642618060112e-02</internalNodes>
      <leafValues>
        8.6725033819675446e-02 -1.2007461786270142e+00</leafValues></_>
    <_>
      <internalNodes>
        0 -1 49584 -2.0032874308526516e-03</internalNodes>
      <leafValues>
        3.4241086244583130e-01 -2.0353627204895020e-01</leafValues></_>
    <_>
      <internalNodes>
        0 -1 14615 -7.8170956112444401e-04</internalNodes>
      <leafValues>
        -4.6932268142700195e-01 1.3369004428386688e-01</leafValues></_></weakClassifiers></stage7>
</opencv_storage>
