<?xml version="1.0"?>
<opencv_storage>
<stage15>
  <maxWeakCount>86</maxWeakCount>
  <stageThreshold>-2.3213436603546143e+00</stageThreshold>
  <weakClassifiers>
    <_>
      <internalNodes>
        0 -1 9194 -268456273 -16385 -21825 -20481 -268455937 -1 -20545
        -16385</internalNodes>
      <leafValues>
        -6.1653554439544678e-01 6.1653554439544678e-01</leafValues></_>
    <_>
      <internalNodes>
        0 -1 19361 -33010 -1 -1 -16777217 2147450628 2147483519 -172
        1971322751</internalNodes>
      <leafValues>
        -5.0317782163619995e-01 5.0317782163619995e-01</leafValues></_>
    <_>
      <internalNodes>
        0 -1 12725 -4 -65538 -1 -2 -11 -1 -3 -1</internalNodes>
      <leafValues>
        -4.8875814676284790e-01 4.8875814676284790e-01</leafValues></_>
    <_>
      <internalNodes>
        0 -1 10337 775827248 1073709055 -1073741825 1073741823
        1073692661 2147483647 2147450879 805257215</internalNodes>
      <leafValues>
        -4.6878334879875183e-01 4.6878334879875183e-01</leafValues></_>
    <_>
      <internalNodes>
        0 -1 9615 -1 -16777217 -1 -16842754 -1 -1 -11 -12</internalNodes>
      <leafValues>
        -4.2856281995773315e-01 4.2856281995773315e-01</leafValues></_>
    <_>
      <internalNodes>
        0 -1 165 -2 -65537 -2 -285278210 -1 -1 -9 -524297</internalNodes>
      <leafValues>
        -3.9624634385108948e-01 3.9624634385108948e-01</leafValues></_>
    <_>
      <internalNodes>
        0 -1 17685 -18 -268435457 -2 -16777218 -1 -1 -10 -134217729</internalNodes>
      <leafValues>
        -3.9039659500122070e-01 3.9039659500122070e-01</leafValues></_>
    <_>
      <internalNodes>
        0 -1 20829 -218 788529151 -2 -16777217 2147450741 2147483647
        -32908 1996488695</internalNodes>
      <leafValues>
        -3.4427425265312195e-01 3.4427425265312195e-01</leafValues></_>
    <_>
      <internalNodes>
        0 -1 15031 -2 -1 -1 -1 -1 -1 -1 234881023</internalNodes>
      <leafValues>
        -3.6546084284782410e-01 3.6546084284782410e-01</leafValues></_>
    <_>
      <internalNodes>
        0 -1 1284 -16798176 1862270975 -16843010 587137022 -32924
        2146959223 -134774924 74973183</internalNodes>
      <leafValues>
        -3.5163143277168274e-01 3.5163143277168274e-01</leafValues></_>
    <_>
      <internalNodes>
        0 -1 16616 -1073807364 -1 -1 -1 -1 -1 -1 -1073741825</internalNodes>
      <leafValues>
        -3.2814076542854309e-01 3.2814076542854309e-01</leafValues></_>
    <_>
      <internalNodes>
        0 -1 17403 -1073807372 -65537 -1 -65538 -3 -1 -3 234651636</internalNodes>
      <leafValues>
        -3.3792209625244141e-01 3.3792209625244141e-01</leafValues></_>
    <_>
      <internalNodes>
        0 -1 17233 -18 -268435457 -10 -1 -1 -1 -9 -134217729</internalNodes>
      <leafValues>
        -3.2083308696746826e-01 3.2083308696746826e-01</leafValues></_>
    <_>
      <internalNodes>
        0 -1 14045 -4178 805306367 -2 -1 2147450751 2147483647 -1 -1</internalNodes>
      <leafValues>
        -3.1744289398193359e-01 3.1744289398193359e-01</leafValues></_>
    <_>
      <internalNodes>
        0 -1 14373 -98308 -65537 -1 -1358954497 -137 -1 -129 788479871</internalNodes>
      <leafValues>
        -2.9370853304862976e-01 2.9370853304862976e-01</leafValues></_>
    <_>
      <internalNodes>
        0 -1 19910 -1073807372 -1 -1 -65537 -3 -1 -139 -1090584716</internalNodes>
      <leafValues>
        -3.1278795003890991e-01 3.1278795003890991e-01</leafValues></_>
    <_>
      <internalNodes>
        0 -1 7055 -268439570 -268435457 -18 -285212674 -129 2147483647
        -137 2147483647</internalNodes>
      <leafValues>
        2.7866038680076599e-01 -2.7866038680076599e-01</leafValues></_>
    <_>
      <internalNodes>
        0 -1 13362 -1 -1 -1 -65537 -1 -1 -1 2147287037</internalNodes>
      <leafValues>
        3.0869615077972412e-01 -3.0869615077972412e-01</leafValues></_>
    <_>
      <internalNodes>
        0 -1 16685 -129 -268435457 -1 -16777217 -137 -1 -137 -1</internalNodes>
      <leafValues>
        -3.1268391013145447e-01 3.1268391013145447e-01</leafValues></_>
    <_>
      <internalNodes>
        0 -1 14918 2147385340 -1 -4 -1 -11 2147483647 2147483645
        218038271</internalNodes>
      <leafValues>
        -2.8694209456443787e-01 2.8694209456443787e-01</leafValues></_>
    <_>
      <internalNodes>
        0 -1 18864 788414256 -1 -1073741825 -268435457 -1073791171 -1
        805257213 788414461</internalNodes>
      <leafValues>
        -3.1404808163642883e-01 3.1404808163642883e-01</leafValues></_>
    <_>
      <internalNodes>
        0 -1 12193 -2 -1 -2 -2 -1 2147483647 -32770 2147450879</internalNodes>
      <leafValues>
        -2.8898695111274719e-01 2.8898695111274719e-01</leafValues></_>
    <_>
      <internalNodes>
        0 -1 9194 -268489170 1879027711 -20754 -1342197761 2147450751 -1
        -49281 1073725439</internalNodes>
      <leafValues>
        2.1455331146717072e-01 -2.1455331146717072e-01</leafValues></_>
    <_>
      <internalNodes>
        0 -1 16372 1879044078 2147483647 -1 -1 2147450751 2147483647 -1
        -1</internalNodes>
      <leafValues>
        -3.0529704689979553e-01 3.0529704689979553e-01</leafValues></_>
    <_>
      <internalNodes>
        0 -1 14317 -16730 -1360068626 -268502016 112131758 -188
        -1896349825 1174369792 2260738</internalNodes>
      <leafValues>
        -3.1955915689468384e-01 3.1955915689468384e-01</leafValues></_>
    <_>
      <internalNodes>
        0 -1 17136 -65540 -65537 -1 -1 -1 -1 -1 -1073741825</internalNodes>
      <leafValues>
        -3.1735152006149292e-01 3.1735152006149292e-01</leafValues></_>
    <_>
      <internalNodes>
        0 -1 6353 -18 -1 -2 -16777218 -129 -1 -9 2013265919</internalNodes>
      <leafValues>
        -2.6247769594192505e-01 2.6247769594192505e-01</leafValues></_>
    <_>
      <internalNodes>
        0 -1 16143 -2 -1 -1 -65537 -129 -1 -11 2013200373</internalNodes>
      <leafValues>
        2.3112674057483673e-01 -2.3112674057483673e-01</leafValues></_>
    <_>
      <internalNodes>
        0 -1 14940 -82 -268435457 -1 -1 -137 -1 -9 -1</internalNodes>
      <leafValues>
        -2.5241988897323608e-01 2.5241988897323608e-01</leafValues></_>
    <_>
      <internalNodes>
        0 -1 19550 251277108 -1359020036 -1 -1359020036 1073708917 -1
        -32908 654114804</internalNodes>
      <leafValues>
        -3.2640427350997925e-01 3.2640427350997925e-01</leafValues></_>
    <_>
      <internalNodes>
        0 -1 7695 -1 -268435457 -1 -1 -1 -1 -1 -1</internalNodes>
      <leafValues>
        -2.7091214060783386e-01 2.7091214060783386e-01</leafValues></_>
    <_>
      <internalNodes>
        0 -1 18698 788270708 -16842753 -1 1073676287 -4 -1 -65540
        1060142964</internalNodes>
      <leafValues>
        -2.8395324945449829e-01 2.8395324945449829e-01</leafValues></_>
    <_>
      <internalNodes>
        0 -1 18962 -65540 -1 -1 -1 -1 -1 -1 -1342242819</internalNodes>
      <leafValues>
        -2.7110058069229126e-01 2.7110058069229126e-01</leafValues></_>
    <_>
      <internalNodes>
        0 -1 11777 -285212894 1861222399 -2 787480575 2147483510
        2147483647 -137 125829111</internalNodes>
      <leafValues>
        -2.5515910983085632e-01 2.5515910983085632e-01</leafValues></_>
    <_>
      <internalNodes>
        0 -1 11675 -18 -268435457 -18 -285212673 -129 -1 -140 2013265919</internalNodes>
      <leafValues>
        2.3676390945911407e-01 -2.3676390945911407e-01</leafValues></_>
    <_>
      <internalNodes>
        0 -1 20279 -1 -268435457 -1 -1 -1 -1 -11 2013265919</internalNodes>
      <leafValues>
        -2.4462103843688965e-01 2.4462103843688965e-01</leafValues></_>
    <_>
      <internalNodes>
        0 -1 9133 1760605744 16580604 -16973836 150798326 2147450740 -3
        -524426 913817599</internalNodes>
      <leafValues>
        -2.9080221056938171e-01 2.9080221056938171e-01</leafValues></_>
    <_>
      <internalNodes>
        0 -1 13365 -18 -1 -1 -1 -1 -1 -1 -1</internalNodes>
      <leafValues>
        -2.4759286642074585e-01 2.4759286642074585e-01</leafValues></_>
    <_>
      <internalNodes>
        0 -1 20534 -1073746398 1858011119 -16777502 -420544530
        2146926420 1199570943 -134777516 1727526900</internalNodes>
      <leafValues>
        -2.9473009705543518e-01 2.9473009705543518e-01</leafValues></_>
    <_>
      <internalNodes>
        0 -1 15808 -18 -1 -1 -1 -1 -1 -1 -1</internalNodes>
      <leafValues>
        -2.6634913682937622e-01 2.6634913682937622e-01</leafValues></_>
    <_>
      <internalNodes>
        0 -1 15219 -1090523290 250544111 -266 787939326 2147450694
        1191182335 -444632000 74842103</internalNodes>
      <leafValues>
        -2.8499040007591248e-01 2.8499040007591248e-01</leafValues></_>
    <_>
      <internalNodes>
        0 -1 19420 -32772 -1 -1 -1 -1 -1 -1 -1073807361</internalNodes>
      <leafValues>
        -2.7954652905464172e-01 2.7954652905464172e-01</leafValues></_>
    <_>
      <internalNodes>
        0 -1 15162 -18 -268435457 -18 -285212673 -137 2147483647 -138
        2147483647</internalNodes>
      <leafValues>
        2.4384230375289917e-01 -2.4384230375289917e-01</leafValues></_>
    <_>
      <internalNodes>
        0 -1 9280 2147434430 2147483647 -1 -1 -32769 2147483647 -1
        1056964607</internalNodes>
      <leafValues>
        -2.8082111477851868e-01 2.8082111477851868e-01</leafValues></_>
    <_>
      <internalNodes>
        0 -1 378 -268435538 -1358954497 -10 -285212674 -137 2013265919
        -138 1962934263</internalNodes>
      <leafValues>
        -3.0099570751190186e-01 3.0099570751190186e-01</leafValues></_>
    <_>
      <internalNodes>
        0 -1 8536 -2 -285278210 -2 -285278210 -138 2147483647 -140
        1416918900</internalNodes>
      <leafValues>
        2.2206187248229980e-01 -2.2206187248229980e-01</leafValues></_>
    <_>
      <internalNodes>
        0 -1 4675 -1359052804 -65537 -1 -16842753 -1 -1 -1 2147418109</internalNodes>
      <leafValues>
        2.4336427450180054e-01 -2.4336427450180054e-01</leafValues></_>
    <_>
      <internalNodes>
        0 -1 11842 -98308 -65537 -1 -65537 -3 -1 -1 2122219519</internalNodes>
      <leafValues>
        -2.4055695533752441e-01 2.4055695533752441e-01</leafValues></_>
    <_>
      <internalNodes>
        0 -1 15017 1191100064 786886654 -196872 15400616 1986690596
        1123987312 1040119508 6356512</internalNodes>
      <leafValues>
        -2.8603756427764893e-01 2.8603756427764893e-01</leafValues></_>
    <_>
      <internalNodes>
        0 -1 15607 -18 -1 -1 -1 -32897 -1 -1 -1</internalNodes>
      <leafValues>
        -2.8449189662933350e-01 2.8449189662933350e-01</leafValues></_>
    <_>
      <internalNodes>
        0 -1 10896 -285294658 -285278209 -1 -268500993 -137 -1 -11
        -131075</internalNodes>
      <leafValues>
        -2.3650078475475311e-01 2.3650078475475311e-01</leafValues></_>
    <_>
      <internalNodes>
        0 -1 16122 788315656 1828651007 -1 2130706431 2147450670 -1
        2147450751 2004713343</internalNodes>
      <leafValues>
        -2.6679655909538269e-01 2.6679655909538269e-01</leafValues></_>
    <_>
      <internalNodes>
        0 -1 14376 -268435476 1862205438 -2 -1359020034 -139 2013265919
        -140 83132276</internalNodes>
      <leafValues>
        2.3152297735214233e-01 -2.3152297735214233e-01</leafValues></_>
    <_>
      <internalNodes>
        0 -1 2635 -18 -285212673 -2 -285212673 -129 2147483647 -137
        2013265919</internalNodes>
      <leafValues>
        2.2234229743480682e-01 -2.2234229743480682e-01</leafValues></_>
    <_>
      <internalNodes>
        0 -1 406 716058146 49213422 -268501010 250474494 1719107396
        133693303 2146369397 113209342</internalNodes>
      <leafValues>
        -3.0152544379234314e-01 3.0152544379234314e-01</leafValues></_>
    <_>
      <internalNodes>
        0 -1 15735 -2 -1 -2 -1 -1 -1 -1 -134217729</internalNodes>
      <leafValues>
        -2.5517362356185913e-01 2.5517362356185913e-01</leafValues></_>
    <_>
      <internalNodes>
        0 -1 14521 -16892368 -285278209 -2 -285278209 -32907 -1 -32907
        -196617</internalNodes>
      <leafValues>
        -2.5973415374755859e-01 2.5973415374755859e-01</leafValues></_>
    <_>
      <internalNodes>
        0 -1 9070 -4098 -1 -1 -1090519042 -1 -1 -1 2147479551</internalNodes>
      <leafValues>
        -2.1802681684494019e-01 2.1802681684494019e-01</leafValues></_>
    <_>
      <internalNodes>
        0 -1 18365 -1358975486 786427884 -16845264 -520683530 2147442454
        1173356543 1440184176 351795188</internalNodes>
      <leafValues>
        -2.8735435009002686e-01 2.8735435009002686e-01</leafValues></_>
    <_>
      <internalNodes>
        0 -1 2458 -2 -1 -1 -16777217 -129 -1 -1 -1</internalNodes>
      <leafValues>
        -2.6152673363685608e-01 2.6152673363685608e-01</leafValues></_>
    <_>
      <internalNodes>
        0 -1 3318 -1 -268435457 -1 -285212673 -129 -1 -9 2147483647</internalNodes>
      <leafValues>
        2.5698205828666687e-01 -2.5698205828666687e-01</leafValues></_>
    <_>
      <internalNodes>
        0 -1 7194 -18 -1342177281 -1 -1 -1 -1 -1 -1</internalNodes>
      <leafValues>
        -2.3388552665710449e-01 2.3388552665710449e-01</leafValues></_>
    <_>
      <internalNodes>
        0 -1 625 788459046 720301950 -268439830 -1494290690 1744791381
        1207926655 2013230964 1718910805</internalNodes>
      <leafValues>
        -2.6061668992042542e-01 2.6061668992042542e-01</leafValues></_>
    <_>
      <internalNodes>
        0 -1 19009 -65537 -1 -1 -1 -1 -1 -1 -1073807361</internalNodes>
      <leafValues>
        -2.6848742365837097e-01 2.6848742365837097e-01</leafValues></_>
    <_>
      <internalNodes>
        0 -1 7092 788463526 788529151 -1 -285212673 -1 -1 -1 2147483647</internalNodes>
      <leafValues>
        2.0817339420318604e-01 -2.0817339420318604e-01</leafValues></_>
    <_>
      <internalNodes>
        0 -1 9182 203489024 73416180 -151715852 70811644 2130509684
        2146926591 2147024887 83156349</internalNodes>
      <leafValues>
        -2.8197374939918518e-01 2.8197374939918518e-01</leafValues></_>
    <_>
      <internalNodes>
        0 -1 11853 -18 -285212673 -18 -285212673 -137 2147483647 -140
        2013265919</internalNodes>
      <leafValues>
        2.4622711539268494e-01 -2.4622711539268494e-01</leafValues></_>
    <_>
      <internalNodes>
        0 -1 10803 -2 -285212673 -1 -268435457 -1 2147483647 -1
        2147483647</internalNodes>
      <leafValues>
        -2.1870929002761841e-01 2.1870929002761841e-01</leafValues></_>
    <_>
      <internalNodes>
        0 -1 18821 -1879060830 788463590 -16777616 1625210864 796884853
        1147142143 1442665812 1081146709</internalNodes>
      <leafValues>
        -2.5804516673088074e-01 2.5804516673088074e-01</leafValues></_>
    <_>
      <internalNodes>
        0 -1 20356 -129 -1 -1 -1 -129 -1 -1 -1</internalNodes>
      <leafValues>
        -2.7606761455535889e-01 2.7606761455535889e-01</leafValues></_>
    <_>
      <internalNodes>
        0 -1 8616 -1 -1 -1 -16842753 -1 -1 -1 2147418111</internalNodes>
      <leafValues>
        2.4327930808067322e-01 -2.4327930808067322e-01</leafValues></_>
    <_>
      <internalNodes>
        0 -1 6250 -1 -1 -2 -16777217 -129 -1 -1 -1</internalNodes>
      <leafValues>
        -2.5577884912490845e-01 2.5577884912490845e-01</leafValues></_>
    <_>
      <internalNodes>
        0 -1 13459 -65540 -268500994 -1 -285278210 -139 -1 2147483517
        1325334527</internalNodes>
      <leafValues>
        -2.3038017749786377e-01 2.3038017749786377e-01</leafValues></_>
    <_>
      <internalNodes>
        0 -1 17589 805269358 805306367 -1 -1 2147450751 2147483647 -1
        2147483647</internalNodes>
      <leafValues>
        1.8059460818767548e-01 -1.8059460818767548e-01</leafValues></_>
    <_>
      <internalNodes>
        0 -1 11925 1073614508 1073704959 -2 805220095 -268484673 -1
        2013214067 402596530</internalNodes>
      <leafValues>
        -2.5281149148941040e-01 2.5281149148941040e-01</leafValues></_>
    <_>
      <internalNodes>
        0 -1 17589 2147483646 1073741823 -1 -1 -32769 -1 -1 -1</internalNodes>
      <leafValues>
        -2.4807858467102051e-01 2.4807858467102051e-01</leafValues></_>
    <_>
      <internalNodes>
        0 -1 1373 -286265694 -420544530 -285278238 552533998 -559259
        2013265911 -2187 880279415</internalNodes>
      <leafValues>
        -2.6889649033546448e-01 2.6889649033546448e-01</leafValues></_>
    <_>
      <internalNodes>
        0 -1 17019 -2 -1 -2 -1 -1 -1 -1 2147483647</internalNodes>
      <leafValues>
        -2.5497332215309143e-01 2.5497332215309143e-01</leafValues></_>
    <_>
      <internalNodes>
        0 -1 2509 -1 -268435457 -2 -285212673 -1 -1 -1 2013265919</internalNodes>
      <leafValues>
        2.1532800793647766e-01 -2.1532800793647766e-01</leafValues></_>
    <_>
      <internalNodes>
        0 -1 17776 -1073807364 -1073741825 -1 -1 -1 -1 -1 -1073741827</internalNodes>
      <leafValues>
        -2.0799617469310760e-01 2.0799617469310760e-01</leafValues></_>
    <_>
      <internalNodes>
        0 -1 20190 -1074249872 -1073807363 -1 -65540 -8388611 -1 -163852
        477920628</internalNodes>
      <leafValues>
        -2.7938830852508545e-01 2.7938830852508545e-01</leafValues></_>
    <_>
      <internalNodes>
        0 -1 20680 -1073840268 -1 -1 -1 -32907 -1 -139 2147254132</internalNodes>
      <leafValues>
        2.2037629783153534e-01 -2.2037629783153534e-01</leafValues></_>
    <_>
      <internalNodes>
        0 -1 12262 -1073971204 -65537 -1 -1 -1 -1 -1 1073545213</internalNodes>
      <leafValues>
        2.1794526278972626e-01 -2.1794526278972626e-01</leafValues></_>
    <_>
      <internalNodes>
        0 -1 11923 -32796 -1073807377 -2 -1114130 -32900 -1 -32780
        900562860</internalNodes>
      <leafValues>
        -2.4561685323715210e-01 2.4561685323715210e-01</leafValues></_>
    <_>
      <internalNodes>
        0 -1 18851 -1073774596 -1 -1 -1 -32771 -1 -1 -65537</internalNodes>
      <leafValues>
        -2.1387723088264465e-01 2.1387723088264465e-01</leafValues></_>
    <_>
      <internalNodes>
        0 -1 12876 788410108 -1 -1 -65537 -1 -1 -1 720920437</internalNodes>
      <leafValues>
        -2.5004759430885315e-01 2.5004759430885315e-01</leafValues></_></weakClassifiers></stage15>
</opencv_storage>
